setup.py
another_neural_net.egg-info/PKG-INFO
another_neural_net.egg-info/SOURCES.txt
another_neural_net.egg-info/dependency_links.txt
another_neural_net.egg-info/requires.txt
another_neural_net.egg-info/top_level.txt
numpy_neural_nets/__init__.py
numpy_neural_nets/basic_mlp.py