Metadata-Version: 1.0
Name: another-neural-net
Version: 0.1
Summary: Packaged fully connected, multilayer neural network written in numpy with data_recipes for testing with sklearn datasets available on github.
Home-page: https://github.com/Ianphorsman/AnotherNeuralNetwork
Author: Ian Horsman
Author-email: ianphorsman@gmail.com
License: MIT
Platform: UNKNOWN
